instacart_log_generator/INFO.py
instacart_log_generator/__init__.py
instacart_log_generator/my_gen_log.py
instacart_log_generator/sample.npy
instacart_log_generator-0.1.6.dist-info/LICENSE.txt
instacart_log_generator-0.1.6.dist-info/METADATA
instacart_log_generator-0.1.6.dist-info/WHEEL
instacart_log_generator-0.1.6.dist-info/top_level.txt
instacart_log_generator-0.1.6.dist-info/RECORD
