Metadata-Version: 2.1
Name: instacart-log-generator
Version: 0.1.6
Summary: Generate fake log based on instacart dataset
Home-page: https://github.com/ehddnr301/instacart-log-generator
Author: ehddnr301
Author-email: dy95032@gmail.com
License: MIT
Platform: UNKNOWN
Requires-Python: >=3.8
License-File: LICENSE.txt
Requires-Dist: numpy (==1.22.0)
